outlooklib/__init__.py
outlooklib/__main__.py
outlooklib/models.py
outlooklib/outlook.py
outlooklib-0.0.12.dist-info/licenses/LICENSE
outlooklib-0.0.12.dist-info/METADATA
outlooklib-0.0.12.dist-info/WHEEL
outlooklib-0.0.12.dist-info/top_level.txt
outlooklib-0.0.12.dist-info/RECORD
