Metadata-Version: 2.4
Name: outlooklib
Version: 0.0.12
Summary: Microsoft Outlook client Python package that uses the requests library.
Author-email: Paulo Portela <portela.paulo@gmail.com>
Maintainer-email: Paulo Portela <portela.paulo@gmail.com>
License-Expression: BSD-3-Clause
Project-URL: Homepage, https://github.com/aghuttun/outlooklib
Project-URL: Documentation, https://github.com/aghuttun/outlooklib/blob/main/README.md
Keywords: Microsoft,Outlook,Python,API,Office365,GraphAPI
Classifier: Programming Language :: Python :: 3.10
Classifier: Programming Language :: Python :: 3.11
Classifier: Programming Language :: Python :: 3.12
Classifier: Programming Language :: Python :: 3.13
Classifier: Programming Language :: Python :: 3.14
Classifier: Programming Language :: Python :: Implementation :: CPython
Classifier: Intended Audience :: Developers
Classifier: Operating System :: POSIX :: Linux
Classifier: Operating System :: Microsoft :: Windows
Classifier: Operating System :: MacOS
Classifier: Operating System :: MacOS :: MacOS X
Requires-Python: >=3.10
License-File: LICENSE
Requires-Dist: requests>=2.0
Requires-Dist: pydantic<2.0.0,>=1.10.13
Provides-Extra: dev
Requires-Dist: twine; extra == "dev"
Requires-Dist: build; extra == "dev"
Dynamic: license-file
